django_object_storage/__init__.py
django_object_storage/b2/__init__.py
django_object_storage/b2/storage.py
django_object_storage/minio/__init__.py
django_object_storage/minio/storage.py
django_object_storage/staticfiles/__init__.py
django_object_storage/staticfiles/storage.py
django_object_storage-0.2.0.dist-info/METADATA
django_object_storage-0.2.0.dist-info/WHEEL
django_object_storage-0.2.0.dist-info/top_level.txt
django_object_storage-0.2.0.dist-info/RECORD
