Metadata-Version: 2.4
Name: django-object-storage
Version: 0.2.0
Summary: Multiple object storage backends for Django (MinIO, Backblaze B2, and more)
Author: Kiều Văn Chương
License: MIT
Project-URL: Homepage, https://github.com/vanchuongkieu/django-object-storage
Project-URL: Repository, https://github.com/vanchuongkieu/django-object-storage
Project-URL: Documentation, https://github.com/vanchuongkieu/django-object-storage#readme
Keywords: django,storage,object-storage,minio,backblaze,b2,s3,django-storage,django-object-storage
Classifier: Development Status :: 3 - Alpha
Classifier: Framework :: Django
Classifier: Framework :: Django :: 3.2
Classifier: Framework :: Django :: 4.0
Classifier: Framework :: Django :: 4.1
Classifier: Framework :: Django :: 4.2
Classifier: Intended Audience :: Developers
Classifier: License :: OSI Approved :: MIT License
Classifier: Operating System :: OS Independent
Classifier: Programming Language :: Python
Classifier: Programming Language :: Python :: 3
Classifier: Programming Language :: Python :: 3.9
Classifier: Programming Language :: Python :: 3.10
Classifier: Programming Language :: Python :: 3.11
Classifier: Topic :: Internet :: WWW/HTTP
Classifier: Topic :: Software Development :: Libraries
Requires-Python: >=3.9
Requires-Dist: django>=3.2
Requires-Dist: minio>=7.1.0
Requires-Dist: requests>=2.25.0
